{"code": "Tbwbq-03aOc", "title": "If you laugh... You're a bad person..", "url": "https://www.youtube.com/watch?v=Tbwbq-03aOc", "thumbnail_url": null, "views": 2000000, "likes": 137000, "duration": "", "embed_code": "https://www.youtube.com/embed/Tbwbq-03aOc", "uploaded_date": "14 Oct 2024", "comments_count": 2815, "comments": [{"comment": "2020: LWIAY\n\n2024: Doomscrolling with Pewdiepie", "commenter_channel_name": "@ItsJoeHut", "likes": 9000, "date": "3 months ago", "fetched_date": "2025-01-19 13:13:59.980795", "replies_count": null, "liked_by_creator": false}, {"comment": "Pewds playing with baby Bjorn is so heartwarming", "commenter_channel_name": "@FriendlyWibberd", "likes": 6000, "date": "3 months ago", "fetched_date": "2025-01-19 13:14:00.020384", "replies_count": null, "liked_by_creator": false}, {"comment": "Pewds happy about folding Laundry the Dad Arc is in full swing", "commenter_channel_name": "@Truffball", "likes": 4000, "date": "3 months ago", "fetched_date": "2025-01-19 13:14:00.200409", "replies_count": null, "liked_by_creator": false}, {"comment": "If Marzia edited this she's really underrated, its really good whoever did it. I wish they'd put who edited vids in the description", "commenter_channel_name": "@anyoldthing", "likes": 495, "date": "3 months ago (edited)", "fetched_date": "2025-01-19 13:14:00.238046", "replies_count": null, "liked_by_creator": false}, {"comment": "5:00 drains battery yes but also it produces glare on the windshield and makes it harder to see at night.", "commenter_channel_name": "@bladedicedragon", "likes": 223, "date": "3 months ago", "fetched_date": "2025-01-19 13:14:00.278439", "replies_count": null, "liked_by_creator": false}, {"comment": "12:15 \"When thoughts cross his mind they get tired\" I'm dead ", "commenter_channel_name": "@mcmuinorac5848", "likes": 526, "date": "3 months ago", "fetched_date": "2025-01-19 13:14:00.318640", "replies_count": null, "liked_by_creator": false}, {"comment": "\"Delete it and feel bad\" Is what you should do!\" \nI love him", "commenter_channel_name": "@N0sdrinker", "likes": 1000, "date": "3 months ago (edited)", "fetched_date": "2025-01-19 13:14:00.362092", "replies_count": null, "liked_by_creator": false}, {"comment": "Pewd\u2019s \u201chella ya\u201d always makes me smile and laugh tbh", "commenter_channel_name": "@Kati_Gory", "likes": 991, "date": "3 months ago", "fetched_date": "2025-01-19 13:14:00.403442", "replies_count": null, "liked_by_creator": false}, {"comment": "All other YouTubers getting caught for grooming or scamming or being bad, meanwhile pewdiepie with a wife,a child and a lovely life is still here with 110 mil subs, I love you Pewdie", "commenter_channel_name": "@MiroKh-q9f", "likes": 121, "date": "2 months ago", "fetched_date": "2025-01-19 13:14:00.440129", "replies_count": 0, "liked_by_creator": false}, {"comment": "12:10 that \"snipers dream\" line made me cry laughing.", "commenter_channel_name": "@onbored9627", "likes": 77, "date": "3 months ago", "fetched_date": "2025-01-19 13:14:00.487421", "replies_count": null, "liked_by_creator": false}, {"comment": "The Chinese mom was actually saying \"you call that breakdancing? You look like raygun\". Which is a great insult in the break dancing world.", "commenter_channel_name": "@lycanlube7484", "likes": 923, "date": "3 months ago", "fetched_date": "2025-01-19 13:14:00.527486", "replies_count": null, "liked_by_creator": false}, {"comment": "Nice to see Pewds upload if you laugh to lose.", "commenter_channel_name": "@22A%E6%9E%97%E6%8B%9B%E7%A5%A5", "likes": 1000, "date": "3 months ago", "fetched_date": "2025-01-19 13:14:00.576105", "replies_count": null, "liked_by_creator": false}, {"comment": "13:34 actually I totally get what you are trying to say and I would say it exactly the same.", "commenter_channel_name": "@pavelkostorek999", "likes": 754, "date": "3 months ago", "fetched_date": "2025-01-19 13:14:00.618259", "replies_count": null, "liked_by_creator": true}, {"comment": "There\u2019s something comforting about seeing a pewds video in the recommendations", "commenter_channel_name": "@adir6094", "likes": 29, "date": "3 months ago", "fetched_date": "2025-01-19 13:14:00.669520", "replies_count": 0, "liked_by_creator": false}, {"comment": "15:19 amazing", "commenter_channel_name": "@abrokeprogrammer", "likes": 22, "date": "3 months ago", "fetched_date": "2025-01-19 13:14:00.707279", "replies_count": 0, "liked_by_creator": false}, {"comment": "5:33 She was saying \"\u53c8\u6389\u4e86\u554a \u53c8\u4f4e\u4e86\". Basically criticizing his dance moves.", "commenter_channel_name": "@premexu2852", "likes": 356, "date": "3 months ago", "fetched_date": "2025-01-19 13:14:00.748512", "replies_count": null, "liked_by_creator": false}, {"comment": "10:25 Dragonborn regaining once again his word of power", "commenter_channel_name": "@BasckedAndJairado", "likes": 427, "date": "3 months ago", "fetched_date": "2025-01-19 13:14:00.792707", "replies_count": null, "liked_by_creator": false}, {"comment": "\u201cThe lord give his toughest trees to his best beavers.\u201d Got me.", "commenter_channel_name": "@voluntaryjerry9835", "likes": 467, "date": "3 months ago", "fetched_date": "2025-01-19 13:14:00.833352", "replies_count": null, "liked_by_creator": false}, {"comment": "Pewds got the most contagious laugh that I literally can\u2019t even stop smiling normally while watching this video.", "commenter_channel_name": "@Jubbano", "likes": 26, "date": "3 months ago", "fetched_date": "2025-01-19 13:14:00.876640", "replies_count": 0, "liked_by_creator": false}, {"comment": "\"Delete it and feel bad\" Is what you should do!\" \nI love him", "commenter_channel_name": "@HannieJeans-w4r", "likes": 236, "date": "3 months ago (edited)", "fetched_date": "2025-01-19 13:14:00.919831", "replies_count": null, "liked_by_creator": false}, {"comment": "Can\u2019t wait to watch him laugh at every clip", "commenter_channel_name": "@afangirlaholic", "likes": 575, "date": "3 months ago", "fetched_date": "2025-01-19 13:14:00.958546", "replies_count": null, "liked_by_creator": false}, {"comment": "8:54 \"HEY! You can't do the thing we told you to do!\"", "commenter_channel_name": "@SwitchFBproductions", "likes": 384, "date": "3 months ago", "fetched_date": "2025-01-19 13:14:00.998797", "replies_count": null, "liked_by_creator": false}, {"comment": "Rainy day, Pewds looking at funny clips, sleeping in, that\u2019s a comfort watch right there", "commenter_channel_name": "@teenagestacker6063", "likes": 93, "date": "3 months ago", "fetched_date": "2025-01-19 13:14:01.038119", "replies_count": 0, "liked_by_creator": false}, {"comment": "Everyone needs to subscribe to pewds cause he\u2019s solid, not ruining his career with controversy, not running scams, and he\u2019s been around forever", "commenter_channel_name": "@NapcanOG", "likes": 36, "date": "3 months ago", "fetched_date": "2025-01-19 13:14:01.077440", "replies_count": null, "liked_by_creator": false}, {"comment": "Haven't seen you in a while, Pewds. It was really nice just laughing with you like the old times. Thanks for the video!", "commenter_channel_name": "@nerotyagi", "likes": 10, "date": "3 months ago", "fetched_date": "2025-01-19 13:14:01.113957", "replies_count": 0, "liked_by_creator": false}, {"comment": "This is the mellowed down version of SKRATTAR DU. F\u00d6RLORAR DU. MANNEEEEEEEN!", "commenter_channel_name": "@LetsbeHonestOfficial", "likes": 369, "date": "3 months ago", "fetched_date": "2025-01-19 13:14:01.154954", "replies_count": null, "liked_by_creator": false}, {"comment": "8:50 he\u2019s stuck at 111million views let\u2019s help him to reach 30 billion subs", "commenter_channel_name": "@EasyWavee", "likes": 514, "date": "3 months ago (edited)", "fetched_date": "2025-01-19 13:14:01.194776", "replies_count": null, "liked_by_creator": false}, {"comment": "The fact you can tell more and more he is a dad now is so sweet to see. Amd really starting to understand, \"why would you do that?\"", "commenter_channel_name": "@jojieanimations2887", "likes": 38, "date": "3 months ago", "fetched_date": "2025-01-19 13:14:01.232106", "replies_count": 0, "liked_by_creator": false}, {"comment": "8:14 it's like 'i coulda gone to the toilet', at least someone still has some common sense. thank you felix", "commenter_channel_name": "@bruce-le-smith", "likes": 11, "date": "3 months ago", "fetched_date": "2025-01-19 13:14:01.270941", "replies_count": 0, "liked_by_creator": false}, {"comment": "5:10 broooooo thats the crying break dance kid ahahahah", "commenter_channel_name": "@firstnamelastname4587", "likes": 6, "date": "3 months ago (edited)", "fetched_date": "2025-01-19 13:14:01.307200", "replies_count": 0, "liked_by_creator": false}, {"comment": "I love that the KitKat guy has a Reeses bag", "commenter_channel_name": "@skudeliFriberg", "likes": 133, "date": "3 months ago", "fetched_date": "2025-01-19 13:14:01.345628", "replies_count": 0, "liked_by_creator": false}, {"comment": "0:16 SHES EVERYWHERE I GO I CANT TAKE IT ANYMORRRRRREEEEEEEEEE AAAAAAAAAAAAAAAAAAAAAAAAAAAAAAAAAAAAAAAAAAAA TUAH", "commenter_channel_name": "@Outplayable", "likes": 151, "date": "3 months ago", "fetched_date": "2025-01-19 13:14:01.386118", "replies_count": null, "liked_by_creator": false}, {"comment": "8:29 \nI just had the same argument.\n\"I bought some candy, you can take some\"\n\"how much can I take?\"\n\"you can take as much as you like\"\n\nWhy is she mad I didn't leave anything for her?\nIf she wanted me to, she should have told me.", "commenter_channel_name": "@anonanon6596", "likes": 66, "date": "3 months ago (edited)", "fetched_date": "2025-01-19 13:14:01.425299", "replies_count": null, "liked_by_creator": false}, {"comment": "My new motto in life now is \"Quit life while you're ahead.\" Thanks pewds!", "commenter_channel_name": "@-O_O-.", "likes": 7, "date": "3 months ago", "fetched_date": "2025-01-19 13:14:01.464338", "replies_count": 0, "liked_by_creator": false}, {"comment": "14:04 DB Tricep Extensions: \u201cH-Here! I got you this drink! N-not like I wanted to..\u201d", "commenter_channel_name": "@requiemforameme1", "likes": 9, "date": "3 months ago", "fetched_date": "2025-01-19 13:14:01.506061", "replies_count": null, "liked_by_creator": false}, {"comment": "8:45 he is not allowed to fill a reese's bag with kitkat", "commenter_channel_name": "@rodrigodhein5641", "likes": 84, "date": "3 months ago", "fetched_date": "2025-01-19 13:14:01.545005", "replies_count": 0, "liked_by_creator": false}, {"comment": "I love how PewDiePie still one of the most normal yt existing", "commenter_channel_name": "@labiba891", "likes": 69, "date": "3 months ago (edited)", "fetched_date": "2025-01-19 13:14:01.584742", "replies_count": null, "liked_by_creator": false}, {"comment": "5:44 pewds was right, the woman said'you fked up.\"", "commenter_channel_name": "@%E6%A2%85%E5%B7%9D%E4%BC%8A%E8%8A%99-k4w", "likes": 270, "date": "3 months ago", "fetched_date": "2025-01-19 13:14:01.624258", "replies_count": null, "liked_by_creator": false}, {"comment": "Ive missed pewdiepie glad hes back i just hope this becomes a gaming channel again. He could play anything and i would watch it.", "commenter_channel_name": "@caromarger2470", "likes": 3, "date": "3 months ago", "fetched_date": "2025-01-19 13:14:01.662804", "replies_count": 0, "liked_by_creator": false}, {"comment": "14:25 thats when you hit all the floor buttons and reverse the awkwardness.", "commenter_channel_name": "@General_Shenanigans", "likes": 5, "date": "3 months ago", "fetched_date": "2025-01-19 13:14:01.699925", "replies_count": 0, "liked_by_creator": false}, {"comment": "4:00 \"you've got a dam to build\" just killed me", "commenter_channel_name": "@ramazanAb", "likes": 122, "date": "3 months ago", "fetched_date": "2025-01-19 13:14:01.737470", "replies_count": null, "liked_by_creator": false}, {"comment": "10:49: Muscle memory.", "commenter_channel_name": "@MoxxoM", "likes": 56, "date": "3 months ago", "fetched_date": "2025-01-19 13:14:01.774622", "replies_count": 0, "liked_by_creator": false}, {"comment": "9:00 Mr.Beast has been dethroned after his glazing. Pewdiepie is king again.", "commenter_channel_name": "@MacaroniGril", "likes": 27, "date": "3 months ago", "fetched_date": "2025-01-19 13:14:01.813499", "replies_count": null, "liked_by_creator": false}, {"comment": "13:07 when you finish writing a new block of code and run the program.", "commenter_channel_name": "@bearmandev", "likes": 2, "date": "2 weeks ago", "fetched_date": "2025-01-19 13:14:01.850803", "replies_count": 0, "liked_by_creator": false}, {"comment": "I've watched you since I was teenager, I don't even call you pewdiepie anymore, seeing you grow up was the best thing I was ever an honor to watch especially seeing you a father now, well done Mr Felix I am proud in so many ways", "commenter_channel_name": "@warmach1nevll47", "likes": 1, "date": "3 months ago", "fetched_date": "2025-01-19 13:14:01.887273", "replies_count": 0, "liked_by_creator": false}, {"comment": "Petition to let Bjorn host meme review", "commenter_channel_name": "@Rvsayshello", "likes": 129, "date": "3 months ago", "fetched_date": "2025-01-19 13:14:01.927229", "replies_count": null, "liked_by_creator": false}, {"comment": "This is why I love this man. His sense of humor is as broken as mine  love ya Felix, lots of love to you and yours n.n", "commenter_channel_name": "@Squishy_tank04", "likes": 8, "date": "3 months ago", "fetched_date": "2025-01-19 13:14:01.964344", "replies_count": 0, "liked_by_creator": false}, {"comment": "If that's the case, I'm always a bad person", "commenter_channel_name": "@blankbudder", "likes": 564, "date": "3 months ago", "fetched_date": "2025-01-19 13:14:02.004096", "replies_count": null, "liked_by_creator": false}, {"comment": "9:26 that's like such smart marketing tho", "commenter_channel_name": "@robijakus6860", "likes": 3, "date": "2 months ago", "fetched_date": "2025-01-19 13:14:02.040191", "replies_count": 0, "liked_by_creator": false}, {"comment": "Jesus christ, \"I bet it echoes when he thinks\" is the best shade I've seen in my entire life", "commenter_channel_name": "@quirkychap", "likes": 5, "date": "3 months ago", "fetched_date": "2025-01-19 13:14:02.078024", "replies_count": 0, "liked_by_creator": false}, {"comment": "Even if the channel is stagnant, This guy will never be replaced  by anyone for the title \"Father of the YouTube\"", "commenter_channel_name": "@builderplays8682", "likes": 114, "date": "3 months ago", "fetched_date": "2025-01-19 13:14:02.119040", "replies_count": null, "liked_by_creator": false}, {"comment": "5:30 she says \"It's the middle of the night, go to bed\"", "commenter_channel_name": "@InvadersDie", "likes": 243, "date": "3 months ago", "fetched_date": "2025-01-19 13:14:02.157465", "replies_count": null, "liked_by_creator": false}, {"comment": "1:10 exactly shows the real feeling of being hit on late at night", "commenter_channel_name": "@Vlol7777", "likes": 67, "date": "3 months ago", "fetched_date": "2025-01-19 13:14:02.198152", "replies_count": null, "liked_by_creator": false}, {"comment": "0:48 that just made my day lmao", "commenter_channel_name": "@bryanfeliciano595", "likes": 3, "date": "3 months ago", "fetched_date": "2025-01-19 13:14:02.233985", "replies_count": 0, "liked_by_creator": false}, {"comment": "8:47 the problem isn't that he's taking too much, it's that he's filling a Reese's bag with KitKats", "commenter_channel_name": "@itsOnlyOlivia", "likes": 1, "date": "2 months ago", "fetched_date": "2025-01-19 13:14:02.272006", "replies_count": 0, "liked_by_creator": false}, {"comment": "I'm litteraly in tears right now \na nostalgia wave just hit me like a truck back when i used to watch ylyl \nand Fridays with PewDiePie \nthank you so much for everything pewds", "commenter_channel_name": "@HASSAN-ws5go", "likes": 171, "date": "3 months ago", "fetched_date": "2025-01-19 13:14:02.310357", "replies_count": null, "liked_by_creator": false}, {"comment": "I forgot how funny it is to watch pewdiepie laugh", "commenter_channel_name": "@Dark%E3%80%85Samurai", "likes": 14, "date": "3 months ago", "fetched_date": "2025-01-19 13:14:02.347770", "replies_count": 0, "liked_by_creator": false}, {"comment": "Love the vid, but you gotta credit the creators. I need to find the channel of the person who made 0:52 and 14:19! I must have more of this content.", "commenter_channel_name": "@EleventhHour78", "likes": 80, "date": "3 months ago", "fetched_date": "2025-01-19 13:14:02.387042", "replies_count": null, "liked_by_creator": false}, {"comment": "Congrats on 110M been here since 111M subs!!!", "commenter_channel_name": "@Yapper-1234", "likes": 2, "date": "1 month ago", "fetched_date": "2025-01-19 13:14:02.424012", "replies_count": 0, "liked_by_creator": false}, {"comment": "13:48 YOU SHOULD HAVE WATCHED  MORE!! YOU MISSED THE BEST THING!!!", "commenter_channel_name": "@MachimoLP", "likes": 14, "date": "3 months ago", "fetched_date": "2025-01-19 13:14:02.462900", "replies_count": null, "liked_by_creator": false}, {"comment": "\u201cQuit life while ur ahead\u201d -pewdiepie 2024", "commenter_channel_name": "@swaggyamw", "likes": 23, "date": "3 months ago", "fetched_date": "2025-01-19 13:14:02.502545", "replies_count": 0, "liked_by_creator": false}, {"comment": "Considering the Mr Beast drama it would be nice to see Pewdiepie take the crown back", "commenter_channel_name": "@revemb4653", "likes": 22, "date": "3 months ago", "fetched_date": "2025-01-19 13:14:02.541605", "replies_count": 0, "liked_by_creator": false}, {"comment": "11:31 Ok, but that one was such a banger I actually started crying from laughing!", "commenter_channel_name": "@NiramBG", "likes": 23, "date": "3 months ago", "fetched_date": "2025-01-19 13:14:02.581218", "replies_count": null, "liked_by_creator": false}, {"comment": "I literally almost choked from how hard I was laughing from the thumbnail alone!! HAH!!", "commenter_channel_name": "@Scorpreqdl", "likes": 1, "date": "2 months ago (edited)", "fetched_date": "2025-01-19 13:14:02.639493", "replies_count": 0, "liked_by_creator": false}, {"comment": "Love you pewds, wishing you and your beautiful family the best! So glad your back! \ufe0f", "commenter_channel_name": "@wolflithay6380", "likes": 1, "date": "2 months ago", "fetched_date": "2025-01-19 13:14:02.732219", "replies_count": 0, "liked_by_creator": false}, {"comment": "10:25 BRO WAS ABOUT TO SAY IT AGAIN", "commenter_channel_name": "@klaouchie", "likes": 60, "date": "3 months ago", "fetched_date": "2025-01-19 13:14:02.769180", "replies_count": 0, "liked_by_creator": false}, {"comment": "What a f\u2019ing nice person", "commenter_channel_name": "@j-lien", "likes": 147, "date": "3 months ago", "fetched_date": "2025-01-19 13:14:02.809575", "replies_count": null, "liked_by_creator": false}, {"comment": "Watching pewds after 5 years, last time I watched him I had just started med school. I graduated med school this September somehow thought of pewds, still love this guy. Never too old for this guy ", "commenter_channel_name": "@papapewdsoursaviour6775", "likes": 15, "date": "3 months ago", "fetched_date": "2025-01-19 13:14:02.846824", "replies_count": 0, "liked_by_creator": false}, {"comment": "9:06 Hell naw BEAT T-series", "commenter_channel_name": "@Flipindipin_44", "likes": 8, "date": "3 months ago", "fetched_date": "2025-01-19 13:14:02.884898", "replies_count": 0, "liked_by_creator": false}, {"comment": "4:57 from what i remember hearing was that it was annoying having the light on (i think it's also obscuring your vision of the road), hence parents saying \"turn the light off or else we'll get arrested and well as kids cops are the big bads you do not want to get in trouble with", "commenter_channel_name": "@TheDarkhoof", "likes": 21, "date": "3 months ago", "fetched_date": "2025-01-19 13:14:02.950900", "replies_count": null, "liked_by_creator": false}, {"comment": "Hey felix, i dont watch a ton of your stuff anymore, but i really do appreciate you for the times when i was watching literally everything you put out. \n\nIm happy for you that you have such a beautiful life. Im sure there are still downs, but surely you know your life is a blessed one. \n\nI wish for you to have beautiful mornings, restful sleep, and the best of health for you, Marzia, and your kid. Thanks for being apart of my childhood.", "commenter_channel_name": "@88Zero", "likes": 23, "date": "3 months ago", "fetched_date": "2025-01-19 13:14:02.988080", "replies_count": 0, "liked_by_creator": false}, {"comment": "5:15 this is mad, bro is doing 3 one-handed airflares and his ma must have expected at least 5", "commenter_channel_name": "@RemusGT", "likes": 20, "date": "3 months ago", "fetched_date": "2025-01-19 13:14:03.022791", "replies_count": 0, "liked_by_creator": false}, {"comment": "i laughed when felix said stucked at 111m, then i scrolled down ", "commenter_channel_name": "@MentionmeIfuGae", "likes": 2, "date": "2 months ago", "fetched_date": "2025-01-19 13:14:03.061803", "replies_count": 0, "liked_by_creator": false}, {"comment": "The ''Sniper's dream'' always gets me haha", "commenter_channel_name": "@GamerKhiladi", "likes": 13, "date": "3 months ago", "fetched_date": "2025-01-19 13:14:03.125676", "replies_count": 0, "liked_by_creator": false}, {"comment": "The 0:57 is so catastrophic I love it ", "commenter_channel_name": "@aoiuemura", "likes": 22, "date": "3 months ago", "fetched_date": "2025-01-19 13:14:03.165673", "replies_count": null, "liked_by_creator": false}, {"comment": "8:56 they didn't have an issue with the amount, it was the bag.", "commenter_channel_name": "@screenname7905", "likes": 11, "date": "3 months ago", "fetched_date": "2025-01-19 13:14:03.203788", "replies_count": 0, "liked_by_creator": false}, {"comment": "The \"quit life\" after seeing Jack's video is just insane.", "commenter_channel_name": "@bautistabarabino5821", "likes": 2, "date": "3 months ago (edited)", "fetched_date": "2025-01-19 13:14:03.268095", "replies_count": 0, "liked_by_creator": false}, {"comment": "Pewds checking the pampers price, and decide to go back as a full time youtuber. lol", "commenter_channel_name": "@afandiyusuf04", "likes": 11, "date": "3 months ago", "fetched_date": "2025-01-19 13:14:03.303429", "replies_count": 0, "liked_by_creator": false}, {"comment": "Haven't had a treat like this in a long time. It helps with the fact that he called us bots earlier today on stream", "commenter_channel_name": "@pakthecube", "likes": 7, "date": "3 months ago (edited)", "fetched_date": "2025-01-19 13:14:03.340939", "replies_count": 0, "liked_by_creator": false}, {"comment": "I haven't had a notification for a pewdiepie video or live in years until this morning,  they for sure had you shadowed", "commenter_channel_name": "@BaNg72983", "likes": 13, "date": "3 months ago", "fetched_date": "2025-01-19 13:14:03.379489", "replies_count": 0, "liked_by_creator": false}, {"comment": "4:19 that guy was about to say the most prophetic and thought provoking statement we've ever heard, but we were robbed of it because he had to clear his throat.", "commenter_channel_name": "@Sovrakha", "likes": 8, "date": "3 months ago", "fetched_date": "2025-01-19 13:14:03.473640", "replies_count": null, "liked_by_creator": false}, {"comment": "If anyone wants to know about the map light, it's because the glare is blinding when the rear-view mirror is in the night-time setting, and that's dangerous if the driver can't see well. Explaining this is tough (even explaining to adults it's easier for others to see them if they have their lights on is hard enough), so parents just say \"it's illegal\" to get dumb kids to do what's safe for the car. They could also go with \"because I say so\".", "commenter_channel_name": "@Tang-qi6zw", "likes": 11, "date": "3 months ago", "fetched_date": "2025-01-19 13:14:03.514427", "replies_count": 0, "liked_by_creator": false}, {"comment": "Let's start a petition for a weekly YLYL episode \n9 year olds really need it", "commenter_channel_name": "@eternaljade97", "likes": 53, "date": "3 months ago", "fetched_date": "2025-01-19 13:14:03.553885", "replies_count": null, "liked_by_creator": false}, {"comment": "4:07 I\u2019m in tears ", "commenter_channel_name": "@Malphas38th", "likes": 1, "date": "2 months ago", "fetched_date": "2025-01-19 13:14:03.591334", "replies_count": 0, "liked_by_creator": false}, {"comment": "5:24   If my son can do this, then I'LL do his homework for him for a week.", "commenter_channel_name": "@livewireOrourke", "likes": 12, "date": "3 months ago", "fetched_date": "2025-01-19 13:14:03.662499", "replies_count": 0, "liked_by_creator": false}, {"comment": "13:21 They're so stupid that they posted their own stupidy lmao, poor horses they don't deserve to deal with that.", "commenter_channel_name": "@Lolo_Sketches", "likes": 27, "date": "3 months ago", "fetched_date": "2025-01-19 13:14:03.710388", "replies_count": 0, "liked_by_creator": false}, {"comment": "I love this new series! I hope to see more of this You Laugh You Lose challenge", "commenter_channel_name": "@ruxxy_j5667", "likes": 17, "date": "3 months ago", "fetched_date": "2025-01-19 13:14:03.748959", "replies_count": null, "liked_by_creator": false}, {"comment": "Hi Pewds, I have been watching you for years. I'm going through some tough times and your videos never failed to cheer me up. Thank you so much.", "commenter_channel_name": "@Yealt", "likes": 1, "date": "3 months ago", "fetched_date": "2025-01-19 13:14:03.787129", "replies_count": 0, "liked_by_creator": false}, {"comment": "6:15 catched up caught me off guard", "commenter_channel_name": "@adityanaidu7526", "likes": 1, "date": "3 months ago", "fetched_date": "2025-01-19 13:14:03.826229", "replies_count": 0, "liked_by_creator": false}, {"comment": "7:00 \"ha ha look at me im so quirky im so silly everybody look at me being funny ha ha!\"", "commenter_channel_name": "@reagansido5823", "likes": 18, "date": "3 months ago", "fetched_date": "2025-01-19 13:14:03.864524", "replies_count": null, "liked_by_creator": false}, {"comment": "9:25 that's the sound of the demons voice", "commenter_channel_name": "@MollyTheLag", "likes": 12, "date": "3 months ago", "fetched_date": "2025-01-19 13:14:03.901875", "replies_count": 0, "liked_by_creator": false}, {"comment": "14:30 She's smoking cotton-bud ", "commenter_channel_name": "@pramana9175", "likes": 14, "date": "3 months ago", "fetched_date": "2025-01-19 13:14:03.943356", "replies_count": null, "liked_by_creator": false}, {"comment": "Wow a live stream and then a video in the same day what a great day", "commenter_channel_name": "@SD12minecraft", "likes": 20, "date": "3 months ago", "fetched_date": "2025-01-19 13:14:04.036539", "replies_count": null, "liked_by_creator": false}, {"comment": "Ksi in the wild. 12:17\nPrime and lunchly businesses fell through ", "commenter_channel_name": "@Mitche23", "likes": 10, "date": "3 months ago", "fetched_date": "2025-01-19 13:14:04.075859", "replies_count": 0, "liked_by_creator": false}, {"comment": "9:01\nLET'S HELP HIM ONCEMORE ", "commenter_channel_name": "@HifzhanDzikri", "likes": 6, "date": "3 months ago", "fetched_date": "2025-01-19 13:14:04.114574", "replies_count": 0, "liked_by_creator": false}, {"comment": "12:07 cool to see KSI once again joining a video", "commenter_channel_name": "@backdoormischief9852", "likes": 9, "date": "3 months ago", "fetched_date": "2025-01-19 13:14:04.207785", "replies_count": 0, "liked_by_creator": false}, {"comment": "It's been a while Pewds did Skrattar du, forlorar du", "commenter_channel_name": "@Ghost-cd5zm", "likes": 58, "date": "3 months ago", "fetched_date": "2025-01-19 13:14:04.249613", "replies_count": null, "liked_by_creator": false}, {"comment": "4:44 \nmy father always said its cuz then he cant see the road, but thats when its dark out. so for the daytime i guess the battery theory can be applied", "commenter_channel_name": "@reileyy3608", "likes": 13, "date": "3 months ago", "fetched_date": "2025-01-19 13:14:04.290851", "replies_count": null, "liked_by_creator": false}, {"comment": "10:39 Kill me laughing. Best clip.", "commenter_channel_name": "@masteronepiece6559", "likes": 1, "date": "3 months ago", "fetched_date": "2025-01-19 13:14:04.326752", "replies_count": 0, "liked_by_creator": false}, {"comment": "0:53 14:07 WHAT'S HER AT?\nWHAT HER  AAAAATTTT-? \nPLEASE SOMEONE ", "commenter_channel_name": "@lakshya5946", "likes": 1, "date": "2 months ago", "fetched_date": "2025-01-19 13:14:04.365368", "replies_count": 0, "liked_by_creator": false}, {"comment": "11:39 BRAZIL MENTIONED RAAAAAHHHH \ud83c\udde7\ud83c\uddf7\ud83c\udde7\ud83c\uddf7\ud83c\udde7\ud83c\uddf7\ud83c\udde7\ud83c\uddf7\ud83c\udde7\ud83c\uddf7\ud83c\udde7\ud83c\uddf7\ud83c\udde7\ud83c\uddf7\ud83c\udde7\ud83c\uddf7\ud83c\udde7\ud83c\uddf7\ud83c\udde7\ud83c\uddf7\ud83c\udde7\ud83c\uddf7\ud83c\udde7\ud83c\uddf7", "commenter_channel_name": "@_equinoxe", "likes": 6, "date": "3 months ago", "fetched_date": "2025-01-19 13:14:04.409030", "replies_count": 0, "liked_by_creator": false}, {"comment": "12:42 True  on the signs here it say fartgupp = speedbump ", "commenter_channel_name": "@DjMiBsweden", "likes": 8, "date": "3 months ago (edited)", "fetched_date": "2025-01-19 13:14:04.447785", "replies_count": 0, "liked_by_creator": false}, {"comment": "ahhh... this brings me back to the YLYL days", "commenter_channel_name": "@tohruthebeginner", "likes": 18, "date": "3 months ago", "fetched_date": "2025-01-19 13:14:04.487628", "replies_count": null, "liked_by_creator": false}, {"comment": "Pewds \nHope You're Doing Well \nLove From India\n\nGive Us Gaming Videos Pewds \nMissing Your Old Funny Gaming Moments", "commenter_channel_name": "@shankyarora5110", "likes": 1, "date": "3 months ago", "fetched_date": "2025-01-19 13:14:04.527216", "replies_count": 0, "liked_by_creator": false}, {"comment": "I have not seen PewDiePie videos in a loooong time, it's interesting he got back into my algorithm :D", "commenter_channel_name": "@Dark_Slayer3000", "likes": 1, "date": "2 months ago", "fetched_date": "2025-01-19 13:14:04.566104", "replies_count": 0, "liked_by_creator": false}, {"comment": "9:12, that's literally Divine intervention to stop you from attending their sermon.", "commenter_channel_name": "@MehrdadParthian", "likes": 11, "date": "3 months ago", "fetched_date": "2025-01-19 13:14:04.602760", "replies_count": 0, "liked_by_creator": false}, {"comment": "damn bro i just checked out ur channel, then coincidentally came upon this lol. im glad Bjorn is having a complete, perfect family with a loving father. Cheers to you Felix!", "commenter_channel_name": "@Black-vz8ss", "likes": 14, "date": "3 months ago", "fetched_date": "2025-01-19 13:14:04.643582", "replies_count": null, "liked_by_creator": false}, {"comment": "The folding laundry part got me I thought it was just going to be brain rot this is actually funny", "commenter_channel_name": "@Natalia-jt9st", "likes": 6, "date": "3 months ago", "fetched_date": "2025-01-19 13:14:04.681767", "replies_count": 0, "liked_by_creator": false}, {"comment": "Favorite line \u201cquit live well your ahead \u201c", "commenter_channel_name": "@Teamswank", "likes": 1, "date": "2 months ago", "fetched_date": "2025-01-19 13:14:04.717947", "replies_count": 0, "liked_by_creator": false}, {"comment": "I always look forward to your new uploads!", "commenter_channel_name": "@NancySantos-u3h", "likes": 2, "date": "3 months ago", "fetched_date": "2025-01-19 13:14:04.757531", "replies_count": 0, "liked_by_creator": false}], "related": []}