{"code": "59ABs_eh9mc", "title": "Burayi Se Samandar Ki Raksha Karne Wala Yodhha: Devara Part 1 Dialogues| Jr NTR | Saif Ali Khan", "url": "https://www.youtube.com/watch?v=59ABs_eh9mc", "thumbnail_url": "https://i.ytimg.com/vi/59ABs_eh9mc/hqdefault.jpg?sqp=-oaymwEnCNACELwBSFryq4qpAxkIARUAAIhCGAHYAQHiAQoIGBACGAY4AUAB&rs=AOn4CLAZ3Dp3vfoA5cEyi5Hplww56--Ayg", "views": 16000, "likes": 144, "duration": 233, "embed_code": "https://www.youtube.com/embed/59ABs_eh9mc", "uploaded_date": "1 Jan 2025", "comments_count": 0, "comments": [], "related": []}