{"code": "S9fVjA4aS_Q", "title": "BEGANA (Music Video): RAGHAV CHAITANYA, KANIKKA KAPUR | BHUSHAN KUMAR", "url": "https://www.youtube.com/watch?v=S9fVjA4aS_Q", "thumbnail_url": "https://i.ytimg.com/vi/S9fVjA4aS_Q/hqdefault.jpg?sqp=-oaymwEnCNACELwBSFryq4qpAxkIARUAAIhCGAHYAQHiAQoIGBACGAY4AUAB&rs=AOn4CLClkwSQel8qO-lOAJ_9Q3UvlMsOuQ", "views": 4000000, "likes": 113000, "duration": 264, "embed_code": "https://www.youtube.com/embed/S9fVjA4aS_Q", "uploaded_date": "Premiered on 7 Jan 2025", "comments_count": 0, "comments": [], "related": []}