{"code": "4SNThp0YiU4", "title": "50 YouTubers Fight For $1,000,000", "url": "https://www.youtube.com/watch?v=4SNThp0YiU4", "thumbnail_url": null, "views": 319000000, "likes": 89000000, "duration": "", "embed_code": "https://www.youtube.com/embed/4SNThp0YiU4", "uploaded_date": "13 Jul 2024", "comments_count": 346023, "comments": [{"comment": "Thank you for 300,000,000 Subscribers!", "commenter_channel_name": "@MrBeast", "likes": 521000, "date": "6 months ago", "fetched_date": "2025-01-19 07:24:31.997093", "replies_count": null, "liked_by_creator": false}, {"comment": "\u201cI have suitcase\u201d is one of the most legendary lines ever said", "commenter_channel_name": "@MattChessco", "likes": 359000, "date": "6 months ago", "fetched_date": "2025-01-19 07:24:32.050944", "replies_count": null, "liked_by_creator": false}, {"comment": "It was an HONOR to be in this ", "commenter_channel_name": "@Jesser", "likes": 91000, "date": "6 months ago", "fetched_date": "2025-01-19 07:24:32.092500", "replies_count": null, "liked_by_creator": true}, {"comment": "\u201cThe true 1 million dollars was the friends we made along the way.\u201d \n\n-MatPat", "commenter_channel_name": "@TheMan4455MRE", "likes": 30000, "date": "5 months ago", "fetched_date": "2025-01-19 07:24:32.132251", "replies_count": null, "liked_by_creator": false}, {"comment": "Speed's comeback was ruthless and became a Frontman", "commenter_channel_name": "@NormativeTraditioned", "likes": 222, "date": "13 days ago", "fetched_date": "2025-01-19 07:24:32.172702", "replies_count": null, "liked_by_creator": false}, {"comment": "I love how all of the pros were so kind to their opponents. True sportsmanship", "commenter_channel_name": "@wildfighter", "likes": 1000, "date": "3 weeks ago", "fetched_date": "2025-01-19 07:24:32.213098", "replies_count": null, "liked_by_creator": false}, {"comment": "The fact that matpat was in the video even tho he retired just makes my day", "commenter_channel_name": "@JamieKorbel", "likes": 16000, "date": "5 months ago", "fetched_date": "2025-01-19 07:24:32.252836", "replies_count": null, "liked_by_creator": false}, {"comment": "The fact that Jaiden said she pulled the 1 million dollar suitcase twice was crazy", "commenter_channel_name": "@VenusXAngelPlayz", "likes": 2000, "date": "1 month ago", "fetched_date": "2025-01-19 07:24:32.294180", "replies_count": null, "liked_by_creator": false}, {"comment": "22:33 the \"She's a demon \" GOT ME ON THE FLOOR LAUGHING ", "commenter_channel_name": "@Variant_Tigress", "likes": 65, "date": "8 days ago", "fetched_date": "2025-01-19 07:24:32.334235", "replies_count": null, "liked_by_creator": false}, {"comment": "An interaction between Miranda Cosgrove, IShowSpeed, and Joey Chestnut was the last thing I expected in a MrBeast video", "commenter_channel_name": "@undeafened", "likes": 132000, "date": "6 months ago", "fetched_date": "2025-01-19 07:24:32.383047", "replies_count": null, "liked_by_creator": false}, {"comment": "Ludwig going in and giving Jaiden a hug was so so precious ", "commenter_channel_name": "@StealthyStellar", "likes": 794, "date": "2 weeks ago", "fetched_date": "2025-01-19 07:24:32.422832", "replies_count": 0, "liked_by_creator": false}, {"comment": "Honestly makes me so happy to still see vikk being a huge YouTuber I\u2019ll never forget his vanilla smp series on the ps3 with dj skellex and the sword house ", "commenter_channel_name": "@isaiahdoxtator1527", "likes": 46, "date": "10 days ago", "fetched_date": "2025-01-19 07:24:32.462874", "replies_count": 0, "liked_by_creator": false}, {"comment": "\"Do you have anything?\"\n\"I have a suitcase\"\n   - What a unique line !", "commenter_channel_name": "@imrankhqn1497", "likes": 16000, "date": "6 months ago", "fetched_date": "2025-01-19 07:24:32.506337", "replies_count": null, "liked_by_creator": false}, {"comment": "Not Speed getting kicked out before even getting in ", "commenter_channel_name": "@Bug0221", "likes": 25000, "date": "6 months ago", "fetched_date": "2025-01-19 07:24:32.558031", "replies_count": null, "liked_by_creator": false}, {"comment": "10:03 Matpat screaming \"retirement begins!\" as if he hasn't been for the past 4 months is hysterical.", "commenter_channel_name": "@StellarGaming07", "likes": 12000, "date": "6 months ago", "fetched_date": "2025-01-19 07:24:32.605240", "replies_count": null, "liked_by_creator": false}, {"comment": "First time I enjoyed a Mr beast challenge", "commenter_channel_name": "@noob_10152", "likes": 9, "date": "9 days ago", "fetched_date": "2025-01-19 07:24:32.644481", "replies_count": 0, "liked_by_creator": false}, {"comment": "\"i have suitcase\" might be the most cold line ever", "commenter_channel_name": "@Typhus109", "likes": 26000, "date": "6 months ago", "fetched_date": "2025-01-19 07:24:32.684523", "replies_count": null, "liked_by_creator": false}, {"comment": "amixem is the goat \n\u201cI have a suitcase\u201d legendary sentence", "commenter_channel_name": "@Nexusoriginel", "likes": 8000, "date": "5 months ago", "fetched_date": "2025-01-19 07:24:32.724887", "replies_count": null, "liked_by_creator": false}, {"comment": "Logan\u2019s anxiety on the cooking challenge all disappeared when he remembered Nick was his teammate", "commenter_channel_name": "@kermitthefrogofficial4274", "likes": 14000, "date": "6 months ago", "fetched_date": "2025-01-19 07:24:32.771468", "replies_count": null, "liked_by_creator": false}, {"comment": "carry was so humble here ", "commenter_channel_name": "@sauravkr6924", "likes": 4000, "date": "2 months ago", "fetched_date": "2025-01-19 07:24:32.812162", "replies_count": null, "liked_by_creator": false}, {"comment": "\"I have a suitcase\" was probably one of the coldest moments asf ", "commenter_channel_name": "@UDIT011", "likes": 4000, "date": "6 months ago", "fetched_date": "2025-01-19 07:24:32.855599", "replies_count": null, "liked_by_creator": false}, {"comment": "Thanks for inviting Carry", "commenter_channel_name": "@mostafaaboussouf6431", "likes": 4, "date": "13 days ago", "fetched_date": "2025-01-19 07:24:32.894095", "replies_count": 0, "liked_by_creator": false}, {"comment": "The best part of this is that there is someone or multiple you can cheer for! I was cheering for Sam and Colby, Jaiden and Odd1's out. I'm stoked for Jaiden! This is also the second challenge she won!", "commenter_channel_name": "@jwolfsilver5397", "likes": 7000, "date": "5 months ago", "fetched_date": "2025-01-19 07:24:32.938492", "replies_count": null, "liked_by_creator": false}, {"comment": "jaiden animations is just casually winning every youtuber mr. beast video at this point", "commenter_channel_name": "@dgavi117", "likes": 597, "date": "6 months ago", "fetched_date": "2025-01-19 07:24:32.981490", "replies_count": null, "liked_by_creator": false}, {"comment": "10:03 Matpat screaming \"retirement begins\" as he hasnt been in it for 4 months is histerical ", "commenter_channel_name": "@JanaMusic-xg7gs", "likes": 2000, "date": "6 months ago", "fetched_date": "2025-01-19 07:24:33.019734", "replies_count": null, "liked_by_creator": false}, {"comment": "anyone else find the \"nom nom nom\" sound effect for jaiden's sugar candy part soooo cuteee???", "commenter_channel_name": "@hails4592", "likes": 16, "date": "7 days ago", "fetched_date": "2025-01-19 07:24:33.056193", "replies_count": 0, "liked_by_creator": false}, {"comment": "Can I take my jacket with me?'' Iconic", "commenter_channel_name": "@jobalert5129", "likes": 3000, "date": "5 months ago", "fetched_date": "2025-01-19 07:24:33.093278", "replies_count": 0, "liked_by_creator": false}, {"comment": "Lilly just casually walking out with $1000 is the most Lilly thing ever", "commenter_channel_name": "@Heyitsanth0ny422", "likes": 2000, "date": "5 months ago", "fetched_date": "2025-01-19 07:24:33.131538", "replies_count": 0, "liked_by_creator": false}, {"comment": "IShowSpeed definitely entered the villain arc when he was asked to judge the cooking challenge", "commenter_channel_name": "@spikyy_boi2892", "likes": 2000, "date": "6 months ago", "fetched_date": "2025-01-19 07:24:33.171848", "replies_count": null, "liked_by_creator": false}, {"comment": "41:12 YESS SHE WON", "commenter_channel_name": "@Its.willa456", "likes": 16, "date": "6 days ago", "fetched_date": "2025-01-19 07:24:33.211024", "replies_count": null, "liked_by_creator": false}, {"comment": "25:26 \u201cI am cooked\u201d\n\u201cYou\u2019ve cooked before?\u201d\n\u201cNo, I am cooked\u201d", "commenter_channel_name": "@hrfutball", "likes": 547, "date": "6 months ago", "fetched_date": "2025-01-19 07:24:33.250985", "replies_count": null, "liked_by_creator": false}, {"comment": "MatPat sacrificing himself with the umbrella is selfless, and that fits him perfectly", "commenter_channel_name": "@The-Chair516", "likes": 935, "date": "6 months ago", "fetched_date": "2025-01-19 07:24:33.289990", "replies_count": null, "liked_by_creator": false}, {"comment": "\"I have, um, suitcase\" is such a fire line.", "commenter_channel_name": "@aSolarEclipse", "likes": 2000, "date": "6 months ago", "fetched_date": "2025-01-19 07:24:33.329737", "replies_count": null, "liked_by_creator": false}, {"comment": "I love the fact that Matt Pat took one for the team and that they put him in the video even though he retired", "commenter_channel_name": "@Just_contet", "likes": 2, "date": "7 days ago", "fetched_date": "2025-01-19 07:24:33.367192", "replies_count": 0, "liked_by_creator": false}, {"comment": "Jaiden Litterly smiled when she opened the briefcase ", "commenter_channel_name": "@BeastPete", "likes": 2000, "date": "5 months ago", "fetched_date": "2025-01-19 07:24:33.404989", "replies_count": 0, "liked_by_creator": false}, {"comment": "Jschlatt got 3 seconds of screentime and Jimmy still called him \u201cSlatt\u201d ", "commenter_channel_name": "@yourlocalmephiles", "likes": 1000, "date": "6 months ago", "fetched_date": "2025-01-19 07:24:33.444570", "replies_count": null, "liked_by_creator": false}, {"comment": "AMIXEM BEING IN THE LAST CONTESTANTS WAS ABSOLUTE GOLD", "commenter_channel_name": "@ur_melodic_melody5817", "likes": 2000, "date": "6 months ago", "fetched_date": "2025-01-19 07:24:33.484661", "replies_count": null, "liked_by_creator": false}, {"comment": "Congrats Jaiden!", "commenter_channel_name": "@%D0%A0%D0%BE%D0%BC%D0%90%D0%BD%D0%B8%D0%BA%D0%B8%D0%BD1337", "likes": 2, "date": "8 days ago", "fetched_date": "2025-01-19 07:24:33.521891", "replies_count": 0, "liked_by_creator": false}, {"comment": "\u201cI have suitcase\u201dmay be one of the most legendary lines ever", "commenter_channel_name": "@Pringles6969", "likes": 1000, "date": "6 months ago", "fetched_date": "2025-01-19 07:24:33.562093", "replies_count": null, "liked_by_creator": false}, {"comment": "Speed's arrival out of nowhere makes me laugh out loud. I wish he'd stayed with them hahaha", "commenter_channel_name": "@shanksroronoa8022", "likes": 272, "date": "6 months ago", "fetched_date": "2025-01-19 07:24:33.603066", "replies_count": null, "liked_by_creator": false}, {"comment": "jj eliminating his teammate and vikk eliminating himself so his teammate could stay LMAO the duality of sidemen", "commenter_channel_name": "@Lunaa_", "likes": 3000, "date": "6 months ago", "fetched_date": "2025-01-19 07:24:33.641417", "replies_count": null, "liked_by_creator": false}, {"comment": "Although Ryan Trahan got out, he still has the best heart", "commenter_channel_name": "@helloeveryonehappy2025", "likes": 1, "date": "20 minutes ago", "fetched_date": "2025-01-19 07:24:33.679009", "replies_count": 0, "liked_by_creator": false}, {"comment": "\"I have... uhm... a suitcase\" Thank you Amixem for this line ", "commenter_channel_name": "@Sansofficial189", "likes": 2000, "date": "6 months ago", "fetched_date": "2025-01-19 07:24:33.717854", "replies_count": null, "liked_by_creator": false}, {"comment": "Michael telling Lilly to take $1000 and sneak it out is the most Michael move ever", "commenter_channel_name": "@FEARTAT3R-rx9dl", "likes": 1000, "date": "6 months ago", "fetched_date": "2025-01-19 07:24:33.754013", "replies_count": null, "liked_by_creator": false}, {"comment": "Botez: Do you have anything?\nAmixem: I have a suitcase.", "commenter_channel_name": "@djgibbs8473", "likes": 2000, "date": "6 months ago", "fetched_date": "2025-01-19 07:24:33.792929", "replies_count": null, "liked_by_creator": false}, {"comment": "I literally saw Jaiden\u2019s POV, congrats to her!  I also saw Ryan, Lexi, and Matpat there, Hehehhe (RIP those players that lost)", "commenter_channel_name": "@aladdinn007", "likes": 1, "date": "6 days ago (edited)", "fetched_date": "2025-01-19 07:24:33.831187", "replies_count": 0, "liked_by_creator": false}, {"comment": "Seeing Lily sneak out with the cash and Jaiden win were both iconic.", "commenter_channel_name": "@Enst%C3%B6ringen", "likes": 274, "date": "4 months ago", "fetched_date": "2025-01-19 07:24:33.869013", "replies_count": 0, "liked_by_creator": false}, {"comment": "Logan picking Nick for the cooking challenge is the biggest plot armor moment", "commenter_channel_name": "@probablynotleo4340", "likes": 2000, "date": "6 months ago", "fetched_date": "2025-01-19 07:24:33.908200", "replies_count": null, "liked_by_creator": false}, {"comment": "seeing the french youtubers i grew up with in a mr beast video is insane. Amixem ate up with that \"i have suitcase\" comment LMAOO", "commenter_channel_name": "@Sky_M4rz", "likes": 1000, "date": "6 months ago", "fetched_date": "2025-01-19 07:24:33.947310", "replies_count": null, "liked_by_creator": false}, {"comment": "27:04 I was laughing so hard", "commenter_channel_name": "@cynthialove4869", "likes": 2, "date": "1 day ago", "fetched_date": "2025-01-19 07:24:33.985973", "replies_count": 0, "liked_by_creator": false}, {"comment": "\"I have ... a suitcase\" was the only thing I never expected", "commenter_channel_name": "@Kdruurjrjed", "likes": 1000, "date": "6 months ago", "fetched_date": "2025-01-19 07:24:34.024836", "replies_count": null, "liked_by_creator": false}, {"comment": "39:20 dude I was so serious and that dude said \"I have a suitcase\" ", "commenter_channel_name": "@shreyanshchourey3169", "likes": 449, "date": "6 months ago", "fetched_date": "2025-01-19 07:24:34.065374", "replies_count": null, "liked_by_creator": false}, {"comment": "matpats noble sacerfice will never be forgotten", "commenter_channel_name": "@Gamingwithbeaurito", "likes": 116, "date": "6 months ago", "fetched_date": "2025-01-19 07:24:34.102626", "replies_count": 0, "liked_by_creator": false}, {"comment": "\u201cRETIREMENT BEGINS\u201d actual legend", "commenter_channel_name": "@Foz482", "likes": 1, "date": "3 days ago", "fetched_date": "2025-01-19 07:24:34.139375", "replies_count": 0, "liked_by_creator": false}, {"comment": "\u201cI have uuuuum\u2026 suitcase\u201d AMIXEM THE GOAT", "commenter_channel_name": "@Marie-So", "likes": 655, "date": "6 months ago", "fetched_date": "2025-01-19 07:24:34.178850", "replies_count": null, "liked_by_creator": false}, {"comment": "\"I have a suitcase\" GOATED line ever", "commenter_channel_name": "@Yahayadokogi1", "likes": 1000, "date": "6 months ago", "fetched_date": "2025-01-19 07:24:34.217942", "replies_count": null, "liked_by_creator": false}, {"comment": "Botez: \"Do you have anything?\"\n\nAmixem: \"I have a suitcase\"\ufe0f", "commenter_channel_name": "@foodiemishra7144", "likes": 2000, "date": "6 months ago", "fetched_date": "2025-01-19 07:24:34.257725", "replies_count": null, "liked_by_creator": false}, {"comment": "The photo he uses for schlatt is crazy, also it is schlatt, not slatt", "commenter_channel_name": "@Theloudestquietkid", "likes": 3, "date": "1 day ago", "fetched_date": "2025-01-19 07:24:34.294584", "replies_count": 0, "liked_by_creator": false}, {"comment": "\"I have uhhh suitcase\" I laughed so hard at that one and so did MrBrest", "commenter_channel_name": "@black_mamban4754", "likes": 658, "date": "6 months ago", "fetched_date": "2025-01-19 07:24:34.335140", "replies_count": null, "liked_by_creator": false}, {"comment": "25:43\n\"I'm cooked\"\n\"Oh you've cooked before!\"\n\"No.. I'm cooked\" ", "commenter_channel_name": "@Emmie-z2d", "likes": 346, "date": "6 months ago", "fetched_date": "2025-01-19 07:24:34.374456", "replies_count": null, "liked_by_creator": false}, {"comment": "Jimmy is a mastermind. Bro just pulled viewer ship from literally every corner of YouTube\u2019s algorithm.", "commenter_channel_name": "@lukifer7230", "likes": 465, "date": "6 months ago", "fetched_date": "2025-01-19 07:24:34.415457", "replies_count": null, "liked_by_creator": false}, {"comment": "No THINKNOODLES AND NO CAYLUS", "commenter_channel_name": "@jdx-rx2vj", "likes": 3, "date": "16 hours ago", "fetched_date": "2025-01-19 07:24:34.452635", "replies_count": 0, "liked_by_creator": false}, {"comment": "\"I have... suitecase...\"\nBest line ever", "commenter_channel_name": "@gouda8275", "likes": 1000, "date": "6 months ago", "fetched_date": "2025-01-19 07:24:34.492720", "replies_count": null, "liked_by_creator": false}, {"comment": "\"I trust him fully\" gets given the umbrella bro did sketch so dirty ", "commenter_channel_name": "@noahgleason9915", "likes": 2000, "date": "6 months ago", "fetched_date": "2025-01-19 07:24:34.532734", "replies_count": null, "liked_by_creator": false}, {"comment": "The way Jimmy laughed when Amixen said I have a suitcase", "commenter_channel_name": "@mbcanuck1911", "likes": 3000, "date": "6 months ago", "fetched_date": "2025-01-19 07:24:34.572613", "replies_count": null, "liked_by_creator": false}, {"comment": "\u201c the true million dollars are the friends that we made along The way and that\u2019s just a theory RETIREMENT BEGINS!!!\u201d\n\nMatpat-", "commenter_channel_name": "@OliviaRackley-x6k", "likes": 6, "date": "8 days ago", "fetched_date": "2025-01-19 07:24:34.609330", "replies_count": 0, "liked_by_creator": false}, {"comment": "Kai & AJ was pure customer service ", "commenter_channel_name": "@Aldgri", "likes": 2000, "date": "6 months ago", "fetched_date": "2025-01-19 07:24:34.649099", "replies_count": null, "liked_by_creator": false}, {"comment": "Speed as a food critic is probably the most normal I\u2019ve ever seen him", "commenter_channel_name": "@MightyMatti", "likes": 632, "date": "6 months ago", "fetched_date": "2025-01-19 07:24:34.688030", "replies_count": null, "liked_by_creator": false}, {"comment": "39:20 \u00ab I have a \u2026 suitecase \u00bb\nthe moment \nmasterclass ", "commenter_channel_name": "@rslthereal", "likes": 403, "date": "6 months ago (edited)", "fetched_date": "2025-01-19 07:24:34.726342", "replies_count": 0, "liked_by_creator": false}, {"comment": "25:50 bro cooked cereal", "commenter_channel_name": "@Zapix991", "likes": 2, "date": "7 days ago", "fetched_date": "2025-01-19 07:24:34.764522", "replies_count": 0, "liked_by_creator": false}, {"comment": "James: are you gonna make a video on this? \n\nJaiden: ehh, only if something interesting happens.", "commenter_channel_name": "@Copycat72", "likes": 280, "date": "5 months ago (edited)", "fetched_date": "2025-01-19 07:24:34.803900", "replies_count": null, "liked_by_creator": false}, {"comment": "\u201cCan I take my jacket with me?\u201d ", "commenter_channel_name": "@Virgox222", "likes": 415, "date": "6 months ago", "fetched_date": "2025-01-19 07:24:34.844437", "replies_count": null, "liked_by_creator": false}, {"comment": "\"Ohayo\" \n\"Ohayo?\"  - Quackity\n\"It's good morning\"\n\"Ohayo\" - Quackity", "commenter_channel_name": "@whoknowswhotf", "likes": 2000, "date": "6 months ago", "fetched_date": "2025-01-19 07:24:34.884947", "replies_count": null, "liked_by_creator": false}, {"comment": "\"UHMM...I HAVE A SUITCASE\" WHAT A LINE!! LEGENDARY!", "commenter_channel_name": "@10LEOSTIANO_RONESSI7", "likes": 633, "date": "6 months ago (edited)", "fetched_date": "2025-01-19 07:24:34.976831", "replies_count": null, "liked_by_creator": false}, {"comment": "I was expecting Gordan Ramsey as the last judge not Speed ", "commenter_channel_name": "@codeandbasketball", "likes": 1000, "date": "6 months ago", "fetched_date": "2025-01-19 07:24:35.021623", "replies_count": null, "liked_by_creator": false}, {"comment": "\"I have a...Uhh suitcase\" That was legendary", "commenter_channel_name": "@jamdungog6218", "likes": 676, "date": "6 months ago (edited)", "fetched_date": "2025-01-19 07:24:35.063773", "replies_count": null, "liked_by_creator": false}, {"comment": "Speed callin out Joey Chestnut for liking to eat is comedy gold", "commenter_channel_name": "@3KLIPSE", "likes": 683, "date": "6 months ago (edited)", "fetched_date": "2025-01-19 07:24:35.136626", "replies_count": null, "liked_by_creator": false}, {"comment": "I watched Jaiden\u2019s version right before this one, and she was SO accurate!", "commenter_channel_name": "@Misty_Moonstar", "likes": 711, "date": "3 months ago", "fetched_date": "2025-01-19 07:24:35.185127", "replies_count": null, "liked_by_creator": false}, {"comment": "Charlie dancing on his way out was such a Charlie thing to do", "commenter_channel_name": "@sacredbleuu", "likes": 364, "date": "6 months ago", "fetched_date": "2025-01-19 07:24:35.230516", "replies_count": null, "liked_by_creator": false}, {"comment": "jimmy getting 50 youtubers is a challange in itself", "commenter_channel_name": "@Hayat_vlogs952", "likes": 421, "date": "6 months ago", "fetched_date": "2025-01-19 07:24:35.302990", "replies_count": null, "liked_by_creator": false}, {"comment": "Botez: \u201cDo you have anything?\u201d\nAmixem: \u201cI have a suitcase\u201d", "commenter_channel_name": "@eratosthene42", "likes": 408, "date": "6 months ago", "fetched_date": "2025-01-19 07:24:35.345361", "replies_count": null, "liked_by_creator": false}, {"comment": "Jschlatt, Matpat, jaiden, theodd1sout and Quackity all together in a mrbeast video is wild", "commenter_channel_name": "@mrsmolbeans", "likes": 991, "date": "6 months ago", "fetched_date": "2025-01-19 07:24:35.386259", "replies_count": null, "liked_by_creator": false}, {"comment": "Picking Speed as a judge is honestly the best decision.", "commenter_channel_name": "@shawnmichaels568", "likes": 980, "date": "6 months ago", "fetched_date": "2025-01-19 07:24:35.456693", "replies_count": null, "liked_by_creator": false}, {"comment": "The way Sushi Riku said, \"I have no idea what's going on.\" in Japanese made me laugh so hard ", "commenter_channel_name": "@theamirmations6101", "likes": 107, "date": "5 months ago", "fetched_date": "2025-01-19 07:24:35.500973", "replies_count": 0, "liked_by_creator": false}, {"comment": "Carry was laughing in the whole video thanks for 777 likes", "commenter_channel_name": "@MrDevill99YT", "likes": 810, "date": "6 months ago (edited)", "fetched_date": "2025-01-19 07:24:35.541440", "replies_count": null, "liked_by_creator": false}, {"comment": "25:37 Logan got so happy when he had Nick ", "commenter_channel_name": "@BROKEZ.", "likes": 298, "date": "6 months ago", "fetched_date": "2025-01-19 07:24:35.618153", "replies_count": null, "liked_by_creator": false}, {"comment": "speed coming back as a judge was a nice touch", "commenter_channel_name": "@JJvonEmiya", "likes": 536, "date": "6 months ago", "fetched_date": "2025-01-19 07:24:35.660190", "replies_count": null, "liked_by_creator": false}, {"comment": "Bro speed being the judge....that move was just lit and perfect ", "commenter_channel_name": "@drj_2k06", "likes": 506, "date": "6 months ago", "fetched_date": "2025-01-19 07:24:35.703893", "replies_count": null, "liked_by_creator": false}, {"comment": "MatPat is a legend for asking for the umbrella", "commenter_channel_name": "@ItsRaven69", "likes": 571, "date": "6 months ago", "fetched_date": "2025-01-19 07:24:35.771556", "replies_count": 0, "liked_by_creator": false}, {"comment": "The fact that most of my favorite youtubers got out during the cookie was crazy", "commenter_channel_name": "@RUERUENEEDSHELP", "likes": 617, "date": "6 months ago", "fetched_date": "2025-01-19 07:24:35.813089", "replies_count": null, "liked_by_creator": false}, {"comment": "SPAGHETTI TACOS?! FOR MIRANDA COSGROVE?! THIS IS GOLD", "commenter_channel_name": "@merjuliusmelano7113", "likes": 7, "date": "7 days ago", "fetched_date": "2025-01-19 07:24:35.852680", "replies_count": 0, "liked_by_creator": false}, {"comment": "Thanks for inviting carry bhaiiiii ", "commenter_channel_name": "@kalarambirkhidwali590", "likes": 269, "date": "6 months ago", "fetched_date": "2025-01-19 07:24:35.901932", "replies_count": null, "liked_by_creator": false}, {"comment": "\"I have a suitcase\" merci Amixem ", "commenter_channel_name": "@camilleg143", "likes": 866, "date": "6 months ago", "fetched_date": "2025-01-19 07:24:35.952119", "replies_count": null, "liked_by_creator": false}, {"comment": "Matpat\u2019s\n\u201cRetirement begins.\u201d\nwas so funny but also sort of hit hard ", "commenter_channel_name": "@bjark4.792", "likes": 481, "date": "4 months ago", "fetched_date": "2025-01-19 07:24:36.021075", "replies_count": 0, "liked_by_creator": false}, {"comment": "30:03 speeds face has me dying ", "commenter_channel_name": "@max_vtv", "likes": 181, "date": "6 months ago", "fetched_date": "2025-01-19 07:24:36.062607", "replies_count": 0, "liked_by_creator": false}, {"comment": "26:30 I was hoping Gordon Ramsay was one of the judges lol", "commenter_channel_name": "@trunxou", "likes": 947, "date": "6 months ago", "fetched_date": "2025-01-19 07:24:36.104866", "replies_count": null, "liked_by_creator": false}, {"comment": "La voix de Mastuuuu ", "commenter_channel_name": "@Diana_fan_byilhan", "likes": 1, "date": "7 hours ago", "fetched_date": "2025-01-19 07:24:36.144547", "replies_count": 0, "liked_by_creator": false}, {"comment": "Ludwig giving Schlatt the umbrella was personal ", "commenter_channel_name": "@Syntecide", "likes": 703, "date": "6 months ago", "fetched_date": "2025-01-19 07:24:36.187497", "replies_count": null, "liked_by_creator": false}, {"comment": "lily walking away with a $1000 is so funny", "commenter_channel_name": "@avaleebee", "likes": 272, "date": "6 months ago", "fetched_date": "2025-01-19 07:24:36.230526", "replies_count": null, "liked_by_creator": false}, {"comment": "Kai - \"The only thing I've cooked is eggs, toast, and cearel.\"\nYou can cook cearel?", "commenter_channel_name": "@elishasun8477", "likes": 558, "date": "6 months ago", "fetched_date": "2025-01-19 07:24:36.270787", "replies_count": null, "liked_by_creator": false}, {"comment": "\u201cThe true 1mil dollars was the friends we made along the way\u201d-matpat", "commenter_channel_name": "@1NightBot__", "likes": 380, "date": "5 months ago", "fetched_date": "2025-01-19 07:24:36.342039", "replies_count": null, "liked_by_creator": false}, {"comment": "\"How did they get this many cybertrucks in one place\" is the most MKBHD thing to say", "commenter_channel_name": "@Propez", "likes": 298, "date": "6 months ago", "fetched_date": "2025-01-19 07:24:36.383878", "replies_count": null, "liked_by_creator": false}, {"comment": "17:19  really a WILD card entry ", "commenter_channel_name": "@SanjaySanjay-vh3gt", "likes": 548, "date": "6 months ago", "fetched_date": "2025-01-19 07:24:36.428857", "replies_count": null, "liked_by_creator": false}, {"comment": "Who else got happy to see CarryMinati here and me", "commenter_channel_name": "@Vancouver_Canucks", "likes": 358, "date": "6 months ago (edited)", "fetched_date": "2025-01-19 07:24:36.500332", "replies_count": null, "liked_by_creator": false}, {"comment": "Charlie dancing his way out of million dollars is the perfect description of my mental state right now.", "commenter_channel_name": "@TinaKim96", "likes": 354, "date": "6 months ago", "fetched_date": "2025-01-19 07:24:36.541475", "replies_count": null, "liked_by_creator": false}, {"comment": "La cara del Rubius  en el 22:02\nEse es mi \u00eddolo", "commenter_channel_name": "@RyongamingGD", "likes": 403, "date": "6 months ago", "fetched_date": "2025-01-19 07:24:36.587105", "replies_count": null, "liked_by_creator": false}, {"comment": "Speed really carry the show", "commenter_channel_name": "@free_1320", "likes": 1, "date": "13 days ago", "fetched_date": "2025-01-19 07:24:36.627232", "replies_count": 0, "liked_by_creator": false}, {"comment": "\"The True Million Dollars Are The Friends We Made Along The Way, And That's No Theory\"\nWell said matthew, well said.", "commenter_channel_name": "@HallowStealth", "likes": 856, "date": "5 months ago", "fetched_date": "2025-01-19 07:24:36.676554", "replies_count": null, "liked_by_creator": false}, {"comment": "Kais cooking was the highlight of this video", "commenter_channel_name": "@robertoJoseSantiago", "likes": 309, "date": "6 months ago", "fetched_date": "2025-01-19 07:24:36.719590", "replies_count": null, "liked_by_creator": false}, {"comment": "Niko's a savage for giving sketch an umbrella ", "commenter_channel_name": "@StephenMei-u7h", "likes": 319, "date": "6 months ago", "fetched_date": "2025-01-19 07:24:36.772075", "replies_count": null, "liked_by_creator": false}], "related": []}