{"code": "Z9WQy9jEY8M", "title": "Giving 10,000 Presents To Kids For Christmas", "url": "https://www.youtube.com/watch?v=Z9WQy9jEY8M", "thumbnail_url": null, "views": 80000000, "likes": 3000000, "duration": "", "embed_code": "https://www.youtube.com/embed/Z9WQy9jEY8M", "uploaded_date": "24 Dec 2019", "comments_count": 171359, "comments": [{"comment": "Subscribe or you will have bad luck", "commenter_channel_name": "@MrBeast", "likes": 163000, "date": "5 years ago", "fetched_date": "2025-01-19 08:32:34.318229", "replies_count": null, "liked_by_creator": false}, {"comment": "That is a good and noble thing you guys are doing.", "commenter_channel_name": "@TheTreyKingShow", "likes": 6000, "date": "5 years ago", "fetched_date": "2025-01-19 08:32:34.398349", "replies_count": null, "liked_by_creator": false}, {"comment": "Dude this guy is the nicest person in the world.", "commenter_channel_name": "@abisondagoat1882", "likes": 19000, "date": "5 years ago", "fetched_date": "2025-01-19 08:32:34.462919", "replies_count": null, "liked_by_creator": false}, {"comment": "My man is carrying our world to be a better place", "commenter_channel_name": "@AP-sabot", "likes": 21000, "date": "5 years ago", "fetched_date": "2025-01-19 08:32:34.539310", "replies_count": null, "liked_by_creator": false}, {"comment": "Mr beast is a blessing to this world", "commenter_channel_name": "@LaneParker-c2e", "likes": 190, "date": "10 months ago", "fetched_date": "2025-01-19 08:32:34.603850", "replies_count": 0, "liked_by_creator": false}, {"comment": "So he\u2019s spent millions for homeless people, given away millions of dollars worth of stuff, gave a house away to a pizza delivery guy and has helped so many people \nGod bless him\n\nWow thx for the likes mind blown never thought I would get this many", "commenter_channel_name": "@jcisneros2630", "likes": 826, "date": "4 years ago (edited)", "fetched_date": "2025-01-19 08:32:34.669606", "replies_count": null, "liked_by_creator": false}, {"comment": "VOTE MR. BEAST FOR PRESIDENT\n\n\nHE HAS A VEEEEEEEEEEEEEEEEEEEEEEEEERY LARGE HEART!", "commenter_channel_name": "@avagarcia1207", "likes": 806, "date": "5 years ago", "fetched_date": "2025-01-19 08:32:34.737689", "replies_count": null, "liked_by_creator": false}, {"comment": "Mrbeast is the only one who can say\n\"ILL TAKE YOUR ENTIRE STOCK\"\nLine and actually do it", "commenter_channel_name": "@MicroClarence", "likes": 558, "date": "5 years ago (edited)", "fetched_date": "2025-01-19 08:32:34.805722", "replies_count": null, "liked_by_creator": false}, {"comment": "i'm now feeling so happy that i'm able to help others by just watching ur videos and u donate,  love u mr.beast and team", "commenter_channel_name": "@MaskClasher", "likes": 74, "date": "9 months ago", "fetched_date": "2025-01-19 08:32:34.880159", "replies_count": 0, "liked_by_creator": false}, {"comment": "He has such a good soul. He just left those toys and didnt even record the reactions. I feel proud as a fan and more importantly as a human being.", "commenter_channel_name": "@ts7308", "likes": 280, "date": "5 years ago", "fetched_date": "2025-01-19 08:32:34.949444", "replies_count": null, "liked_by_creator": false}, {"comment": "When you do this, I actually get some level of hope to humanity", "commenter_channel_name": "@Blertie", "likes": 292, "date": "5 years ago", "fetched_date": "2025-01-19 08:32:35.017282", "replies_count": null, "liked_by_creator": false}, {"comment": "Mr. Beast gives way more than any other politician, imagine him being the president, the entire country would be happy and thankful to this man.", "commenter_channel_name": "@charliemacx409", "likes": 639, "date": "4 years ago", "fetched_date": "2025-01-19 08:32:35.078328", "replies_count": null, "liked_by_creator": false}, {"comment": "I'm happy when you're helping people", "commenter_channel_name": "@farahhamdouche", "likes": 14, "date": "1 year ago", "fetched_date": "2025-01-19 08:32:35.134410", "replies_count": 0, "liked_by_creator": false}, {"comment": "Got to respect the fact he keeps children off the camera were others would seek for their reaction", "commenter_channel_name": "@LdjaixhwUz", "likes": 4000, "date": "3 years ago", "fetched_date": "2025-01-19 08:32:35.197081", "replies_count": null, "liked_by_creator": false}, {"comment": "All he wants to do is make people happy and make the world a better place.", "commenter_channel_name": "@AcyNights", "likes": 4000, "date": "5 years ago (edited)", "fetched_date": "2025-01-19 08:32:35.266055", "replies_count": null, "liked_by_creator": false}, {"comment": "Am I the only one who's crying here? Jimmy and his squad are totally gifts from heaven ", "commenter_channel_name": "@paulinepetalcorin559", "likes": 246, "date": "4 years ago", "fetched_date": "2025-01-19 08:32:35.317162", "replies_count": null, "liked_by_creator": false}, {"comment": "\u042f \u0445\u043e\u0442\u044c \u0438 \u0438\u0437 \u0420\u043e\u0441\u0441\u0438\u0438 \u043d\u043e \u0434\u043e\u043b\u0436\u043d\u0430 \u0441\u043a\u0430\u0437\u0430\u0442\u044c, \u0432\u044b \u0434\u0435\u043b\u0430\u0435\u0442\u0435 \u0442\u0430\u043a \u043c\u043d\u043e\u0433\u043e \u043f\u043e\u043b\u044c\u0437\u044b \u0434\u043b\u044f \u0432\u0441\u0435\u0433\u043e \u043c\u0438\u0440\u0430! ", "commenter_channel_name": "@%D0%9C%D0%B0%D1%80%D0%B8%D0%A1%D0%B5%D0%BB%D0%B8%D0%B2%D0%B5%D1%80%D1%81%D1%82%D0%BE%D0%B2%D0%B0", "likes": 14, "date": "1 year ago (edited)", "fetched_date": "2025-01-19 08:32:35.358344", "replies_count": null, "liked_by_creator": false}, {"comment": "\u201cWe helped hundreds, maybe thousands of people\u201d\n\nMe: you probably helped millions", "commenter_channel_name": "@sabre5119", "likes": 810, "date": "4 years ago", "fetched_date": "2025-01-19 08:32:35.397595", "replies_count": null, "liked_by_creator": false}, {"comment": "Spending tons of money for himself: *No*\n\nSpending tons of money for others: *Yes*", "commenter_channel_name": "@TheLUCKGOD1", "likes": 1000, "date": "4 years ago", "fetched_date": "2025-01-19 08:32:35.446717", "replies_count": null, "liked_by_creator": false}, {"comment": "jimmy does literally anything\n\n\neveryone liked that", "commenter_channel_name": "@zoeg1013", "likes": 272, "date": "5 years ago (edited)", "fetched_date": "2025-01-19 08:32:35.485610", "replies_count": null, "liked_by_creator": false}, {"comment": "me encanta ver tus videos porque ayudas a personas q de verdad lo necesitan", "commenter_channel_name": "@dorcasizaguirre2039", "likes": 1, "date": "3 months ago", "fetched_date": "2025-01-19 08:32:35.522300", "replies_count": 0, "liked_by_creator": false}, {"comment": "\u201cThe food will last until monday\u201d \nMrBeast: \u201cis that a challenge?\u201d", "commenter_channel_name": "@jayxproductions", "likes": 469, "date": "5 years ago", "fetched_date": "2025-01-19 08:32:35.559874", "replies_count": 0, "liked_by_creator": false}, {"comment": "This is why he has so many friends. His friends probably enjoy helping him and many other people out. Making people happy & dreams come true is what Mr. Beast is amazing at. This is why everyone likes him.", "commenter_channel_name": "@stephaniebeaton", "likes": 308, "date": "4 years ago", "fetched_date": "2025-01-19 08:32:35.598337", "replies_count": null, "liked_by_creator": false}, {"comment": "I think it\u2019s so sweet that he spends millions on other people even though he doesn\u2019t know them", "commenter_channel_name": "@jadedarden6070", "likes": 736, "date": "3 years ago", "fetched_date": "2025-01-19 08:32:35.637278", "replies_count": null, "liked_by_creator": false}, {"comment": "Jimmy nunca me voy a cansar de admirar tu generosidad eres demasiado de buena persona qu\u00e9 bello eres nunca cambies qu\u00e9 coraz\u00f3n tan precioso el que tienes qu\u00e9 alma tan transparente la tuya te admiro much\u00edsimo sigue adelante y nunca te canses de ayudar a los dem\u00e1s te felicito", "commenter_channel_name": "@mariagomez8435", "likes": 9, "date": "6 months ago", "fetched_date": "2025-01-19 08:32:35.674907", "replies_count": 0, "liked_by_creator": false}, {"comment": "Imagine this..\nMrbeast: Becoming president for a day\nEveryone: Do it again", "commenter_channel_name": "@jordanlee042008", "likes": 510, "date": "4 years ago", "fetched_date": "2025-01-19 08:32:35.715211", "replies_count": null, "liked_by_creator": false}, {"comment": "MrBeast: \u201cForm a line\u201d\n\nEveryone: Charges and crowds around him", "commenter_channel_name": "@thatoneboi4928", "likes": 444, "date": "4 years ago", "fetched_date": "2025-01-19 08:32:35.753874", "replies_count": null, "liked_by_creator": false}, {"comment": "Imagine being Jimmy's kid- he would have the best stories, get whatever he wants, and have the best holidays", "commenter_channel_name": "@jackryan3518", "likes": 370, "date": "4 years ago", "fetched_date": "2025-01-19 08:32:35.791293", "replies_count": null, "liked_by_creator": false}, {"comment": "Que hermosa ayuda  muchas bendiciones Jimmy  y gracias por siempre estar ah\u00ed para toda la Gente y para sus seguidores tambi\u00e9n ", "commenter_channel_name": "@EstefaniaMoris", "likes": 48, "date": "1 year ago", "fetched_date": "2025-01-19 08:32:35.829890", "replies_count": 0, "liked_by_creator": false}, {"comment": "This the closest person in the world to actually be santa", "commenter_channel_name": "@steelo07-y2v", "likes": 356, "date": "4 years ago", "fetched_date": "2025-01-19 08:32:35.868286", "replies_count": null, "liked_by_creator": false}, {"comment": "I swear world peace would be achieved if everyone had his heart.", "commenter_channel_name": "@wjm21298", "likes": 303, "date": "4 years ago", "fetched_date": "2025-01-19 08:32:35.907136", "replies_count": null, "liked_by_creator": false}, {"comment": "Santa: Everyone loves me!!\n\n\nMr beast: I\u2019m gonna end this man\u2019s whole career", "commenter_channel_name": "@anshadabdulrahman7529", "likes": 327, "date": "4 years ago", "fetched_date": "2025-01-19 08:32:35.946427", "replies_count": null, "liked_by_creator": false}, {"comment": "son is entertaining asf ", "commenter_channel_name": "@ysntony_", "likes": 35, "date": "1 year ago", "fetched_date": "2025-01-19 08:32:35.983989", "replies_count": 0, "liked_by_creator": false}, {"comment": "My daughter loves this so much and now wants to give away everything in our house", "commenter_channel_name": "@RelyeaGaming", "likes": 250, "date": "5 years ago", "fetched_date": "2025-01-19 08:32:36.024050", "replies_count": null, "liked_by_creator": false}, {"comment": "If mrbeast runs out of money everyone would help him because he is the best", "commenter_channel_name": "@Azzam-pz5qy", "likes": 2000, "date": "4 years ago", "fetched_date": "2025-01-19 08:32:36.062554", "replies_count": null, "liked_by_creator": false}, {"comment": "Mr beast is the most light hearted person in the world he should win so many awards\nEdit:omg thanks for the likes", "commenter_channel_name": "@jamieson4454", "likes": 270, "date": "4 years ago (edited)", "fetched_date": "2025-01-19 08:32:36.103101", "replies_count": null, "liked_by_creator": false}, {"comment": "I swear Mrbeast is just an angel sent from the heavens to help those in need", "commenter_channel_name": "@Wyatt-gq9gu", "likes": 5, "date": "6 months ago", "fetched_date": "2025-01-19 08:32:36.140334", "replies_count": 0, "liked_by_creator": false}, {"comment": "Mr Beast should have won person of the year", "commenter_channel_name": "@Vincent-qg8ul", "likes": 3000, "date": "5 years ago", "fetched_date": "2025-01-19 08:32:36.178161", "replies_count": null, "liked_by_creator": false}, {"comment": "When the meme guy said \u201cKobe\u201d, that hurt", "commenter_channel_name": "@Jeffreyscollection", "likes": 1000, "date": "4 years ago", "fetched_date": "2025-01-19 08:32:36.218069", "replies_count": null, "liked_by_creator": false}, {"comment": "If this man isn\u2019t president I will steal the beans.", "commenter_channel_name": "@yayayaayy", "likes": 277, "date": "4 years ago", "fetched_date": "2025-01-19 08:32:36.255780", "replies_count": null, "liked_by_creator": false}, {"comment": "Thanks!", "commenter_channel_name": "@ViratTendulkar-hy9ht", "likes": 1, "date": "1 year ago", "fetched_date": "2025-01-19 08:32:36.293776", "replies_count": 0, "liked_by_creator": false}, {"comment": "\"Ever heard of a elf on a shelf?\" \"Chandler you're a special human being\" best conversation between Jimmy and chandler.", "commenter_channel_name": "@RexLayZz", "likes": 1000, "date": "4 years ago (edited)", "fetched_date": "2025-01-19 08:32:36.333468", "replies_count": null, "liked_by_creator": false}, {"comment": "Mr.Beast is too pure. He needs to be kept in this world forever.", "commenter_channel_name": "@Mezigen", "likes": 360, "date": "5 years ago", "fetched_date": "2025-01-19 08:32:36.371770", "replies_count": null, "liked_by_creator": false}, {"comment": "Imagine being told that Santa isn\u2019t real but yet we\u2019re seeing actually footage", "commenter_channel_name": "@LUXS.", "likes": 588, "date": "4 years ago", "fetched_date": "2025-01-19 08:32:36.410455", "replies_count": null, "liked_by_creator": false}, {"comment": "Jimmy is the best kindest person ever", "commenter_channel_name": "@manlymanyo2511", "likes": 4, "date": "11 months ago", "fetched_date": "2025-01-19 08:32:36.448485", "replies_count": 0, "liked_by_creator": false}, {"comment": "Mr Beast: Walks into a store\nCashiers: Here we go again.\n(I have never had so many likes! Thanks)", "commenter_channel_name": "@42starshine", "likes": 576, "date": "4 years ago (edited)", "fetched_date": "2025-01-19 08:32:36.487304", "replies_count": null, "liked_by_creator": false}, {"comment": "lest take a moment to honor all the people who need to scan every prduct", "commenter_channel_name": "@calebzamudio4979", "likes": 736, "date": "4 years ago", "fetched_date": "2025-01-19 08:32:36.525886", "replies_count": null, "liked_by_creator": false}, {"comment": "This is incredible. Bringing such joy to so many. The world needs more of you", "commenter_channel_name": "@Themegaminded", "likes": 825, "date": "5 years ago", "fetched_date": "2025-01-19 08:32:36.566661", "replies_count": null, "liked_by_creator": false}, {"comment": " Muchas gracias mrBeast por darle a esos ni\u00f1os", "commenter_channel_name": "@LenoskaHern%C3%A1ndez", "likes": 1, "date": "2 weeks ago", "fetched_date": "2025-01-19 08:32:36.602293", "replies_count": 0, "liked_by_creator": false}, {"comment": "\u201cEver heard of elf on the shelf?\u201d \nChandler literally got a genuine reaction from Jimmy. That was hilarious. ", "commenter_channel_name": "@picsandpsalterystudios996", "likes": 1000, "date": "3 years ago", "fetched_date": "2025-01-19 08:32:36.643861", "replies_count": null, "liked_by_creator": false}, {"comment": "I get so upset when some people just take whatever he is giving and don't even say thank you :((", "commenter_channel_name": "@casablancaswife", "likes": 1000, "date": "4 years ago", "fetched_date": "2025-01-19 08:32:36.682929", "replies_count": null, "liked_by_creator": false}, {"comment": "Mrbeast: walks into store\n\nManager of the store: P  A  R  A  D  I  S  E", "commenter_channel_name": "@piercereid653", "likes": 531, "date": "4 years ago", "fetched_date": "2025-01-19 08:32:36.720717", "replies_count": null, "liked_by_creator": false}, {"comment": "I love watching your videos", "commenter_channel_name": "@AmitielSobolewski", "likes": 3, "date": "4 months ago", "fetched_date": "2025-01-19 08:32:36.759349", "replies_count": 0, "liked_by_creator": false}, {"comment": "everyone vote mr beast for president.\n\nstop taking this seriously ", "commenter_channel_name": "@JMEEF13", "likes": 25000, "date": "5 years ago (edited)", "fetched_date": "2025-01-19 08:32:36.798723", "replies_count": null, "liked_by_creator": false}, {"comment": "When the people who deserve to be wealthy become wealthy", "commenter_channel_name": "@gaithsaleh7880", "likes": 352, "date": "4 years ago", "fetched_date": "2025-01-19 08:32:36.836874", "replies_count": null, "liked_by_creator": false}, {"comment": "can. we appreciate that he didn't use the children for views", "commenter_channel_name": "@codapunchard3218", "likes": 373, "date": "5 years ago", "fetched_date": "2025-01-19 08:32:36.876447", "replies_count": null, "liked_by_creator": false}, {"comment": "If only all the other YouTubers were just as kind hearted as Jimmy!", "commenter_channel_name": "@HAXTHEHACKER", "likes": 4, "date": "7 months ago", "fetched_date": "2025-01-19 08:32:36.911705", "replies_count": 0, "liked_by_creator": false}, {"comment": "Thanos:     \u201cI am inevitable\u201d\nIron Man:  \u201cI am Iron Man\u201d\n\nMr Beast:  \u201cI am Santa Claus\u201d", "commenter_channel_name": "@hassansaeed6215", "likes": 496, "date": "5 years ago", "fetched_date": "2025-01-19 08:32:36.954772", "replies_count": null, "liked_by_creator": false}, {"comment": "Who wants Mr.Beast to be a president?", "commenter_channel_name": "@alexcamon8803", "likes": 1000, "date": "4 years ago", "fetched_date": "2025-01-19 08:32:36.992599", "replies_count": null, "liked_by_creator": false}, {"comment": "I cracked when Chandler said:\n\u201cYou Ever Seen Elf On The Shelf\u201d", "commenter_channel_name": "@SirToxicBoy", "likes": 1000, "date": "4 years ago (edited)", "fetched_date": "2025-01-19 08:32:37.032330", "replies_count": null, "liked_by_creator": false}, {"comment": "\u041d\u0430\u043a\u043e\u043d\u0435\u0446-\u0442\u043e \u043f\u043e\u044f\u0432\u0438\u043b\u0441\u044f \u043f\u0435\u0440\u0435\u0432\u043e\u0434 \u044d\u0442\u043e\u0433\u043e \u0432\u0438\u0434\u0435\u043e", "commenter_channel_name": "@Denn204", "likes": 4, "date": "10 months ago", "fetched_date": "2025-01-19 08:32:37.069073", "replies_count": 0, "liked_by_creator": false}, {"comment": "Mr beast: here is 2000 dollars for tuition \n\nChris: And here\u2019s 13 cents", "commenter_channel_name": "@bouheyrbaluch7909", "likes": 1000, "date": "5 years ago", "fetched_date": "2025-01-19 08:32:37.110066", "replies_count": null, "liked_by_creator": false}, {"comment": "boi how doesnt mr beast have a nobel peace prize.", "commenter_channel_name": "@youtubeblonde", "likes": 1000, "date": "5 years ago", "fetched_date": "2025-01-19 08:32:37.149634", "replies_count": null, "liked_by_creator": false}, {"comment": "Food bank lady: \u201cThis will only last till Monday.\u201d  \nMrBeast:\u201dSay no more we will just buy out all the stores!\u201d", "commenter_channel_name": "@iceninja8591", "likes": 435, "date": "4 years ago", "fetched_date": "2025-01-19 08:32:37.189356", "replies_count": null, "liked_by_creator": false}, {"comment": "Hoy 28 de diciembre me suscrib\u00ed a tu canal , felicidades bro eres una persona que tiene mucho dinero y es una persona ejemplar", "commenter_channel_name": "@lenchorodas6519", "likes": 4, "date": "1 year ago", "fetched_date": "2025-01-19 08:32:37.227077", "replies_count": 0, "liked_by_creator": false}, {"comment": "Mr Beast is slowly changing the world for the better ", "commenter_channel_name": "@J1mmyC", "likes": 1000, "date": "5 years ago", "fetched_date": "2025-01-19 08:32:37.265011", "replies_count": null, "liked_by_creator": false}, {"comment": "it makes me smile when he was giving away those things at the donut place, thinking that one day it will happen to me.", "commenter_channel_name": "@bonniehall5885", "likes": 240, "date": "4 years ago", "fetched_date": "2025-01-19 08:32:37.304430", "replies_count": null, "liked_by_creator": false}, {"comment": "My parents: Santa doesn\u2019t exist\nMe: A R E   Y O U   S U R E   A B O U T   T H A T", "commenter_channel_name": "@heavymetallovrrr", "likes": 517, "date": "5 years ago", "fetched_date": "2025-01-19 08:32:37.343426", "replies_count": null, "liked_by_creator": false}, {"comment": "You guys really do amazing things for people!", "commenter_channel_name": "@britth7412", "likes": 4, "date": "10 months ago", "fetched_date": "2025-01-19 08:32:37.380998", "replies_count": null, "liked_by_creator": false}, {"comment": "Mr beast walks into a store\nThe store: finally a good selling day", "commenter_channel_name": "@CJ-2", "likes": 445, "date": "4 years ago", "fetched_date": "2025-01-19 08:32:37.426585", "replies_count": null, "liked_by_creator": false}, {"comment": "Jimmy: \u201cNow we need some tissuuuees...\u201d\n\nChandler: \u201cEver heard Elf On a Shelf\u201d", "commenter_channel_name": "@KingRifti", "likes": 358, "date": "4 years ago", "fetched_date": "2025-01-19 08:32:37.465231", "replies_count": null, "liked_by_creator": false}, {"comment": "Only one thing is bigger than his wallet,\n\nHis heart", "commenter_channel_name": "@strqngerr", "likes": 491, "date": "4 years ago", "fetched_date": "2025-01-19 08:32:37.503669", "replies_count": null, "liked_by_creator": false}, {"comment": "MrBeast international fans button ", "commenter_channel_name": "@annazangz6798", "likes": 6, "date": "2 months ago", "fetched_date": "2025-01-19 08:32:37.550340", "replies_count": 0, "liked_by_creator": false}, {"comment": "Im convinced he has unlimited money now", "commenter_channel_name": "@vlad.ff284", "likes": 997, "date": "4 years ago", "fetched_date": "2025-01-19 08:32:37.594827", "replies_count": null, "liked_by_creator": false}, {"comment": "\u201cNo more beans\u201d\n\n\u201cb e a n s.\u201d", "commenter_channel_name": "@PracticalNeuron", "likes": 506, "date": "5 years ago", "fetched_date": "2025-01-19 08:32:37.635080", "replies_count": null, "liked_by_creator": false}, {"comment": "I honestly wouldn\u2019t be surprised if mr beast was Santa", "commenter_channel_name": "@heathertibshraeny3585", "likes": 404, "date": "4 years ago", "fetched_date": "2025-01-19 08:32:37.682565", "replies_count": null, "liked_by_creator": false}, {"comment": "Dios te bendiga x tu gesto hacia las personas necesitadas", "commenter_channel_name": "@melisajofre5195", "likes": 1, "date": "7 months ago", "fetched_date": "2025-01-19 08:32:37.719335", "replies_count": 0, "liked_by_creator": false}, {"comment": "Mr beast: \u201cYa wanna free laptop?\u201d\nRandom people: \u201cUhhhhhh\u201d\nMr beast: \u201cSure ya do.\u201d", "commenter_channel_name": "@coolestsand1388", "likes": 260, "date": "5 years ago", "fetched_date": "2025-01-19 08:32:37.757618", "replies_count": 0, "liked_by_creator": false}, {"comment": "It's true charity, as he doesn't wants to show children.", "commenter_channel_name": "@yumnjame546", "likes": 654, "date": "4 years ago", "fetched_date": "2025-01-19 08:32:37.802047", "replies_count": null, "liked_by_creator": false}, {"comment": "He\u2019s literally doing more than the government", "commenter_channel_name": "@ozicarrillo4225", "likes": 2000, "date": "4 years ago", "fetched_date": "2025-01-19 08:32:37.839986", "replies_count": null, "liked_by_creator": false}, {"comment": "Im in england 20 degrees for us is a blessing for you it being freezing is crazy", "commenter_channel_name": "@SerialDesignationL-z3h", "likes": 1, "date": "1 month ago", "fetched_date": "2025-01-19 08:32:37.879187", "replies_count": 0, "liked_by_creator": false}, {"comment": "Cashier: How many blankets do you want?\nMrbeast: yes", "commenter_channel_name": "@strikingblazer760", "likes": 350, "date": "4 years ago", "fetched_date": "2025-01-19 08:32:37.917152", "replies_count": null, "liked_by_creator": false}, {"comment": "Santa: \"I am Best Gifter\"\nMrBeast: \" Hold My Chandler\"", "commenter_channel_name": "@beastxfaheem7765", "likes": 645, "date": "4 years ago", "fetched_date": "2025-01-19 08:32:37.961218", "replies_count": null, "liked_by_creator": false}, {"comment": "Vote mr.beast for president\nBeast of best", "commenter_channel_name": "@simpaciaga4751", "likes": 2000, "date": "5 years ago", "fetched_date": "2025-01-19 08:32:38.000660", "replies_count": null, "liked_by_creator": false}, {"comment": "\u0422\u044b \u0441\u0430\u043c\u044b\u0439 \u041b\u0423\u0427\u0428\u0418\u0419 \u0427\u0415\u041b\u041e\u0412\u0415\u041a \u0412 \u041c\u0418\u0420\u0415", "commenter_channel_name": "@%D0%9E%D0%BB%D1%8F%D0%A5%D0%B0%D1%80%D1%83%D0%BD", "likes": 4, "date": "1 year ago", "fetched_date": "2025-01-19 08:32:38.037249", "replies_count": 0, "liked_by_creator": false}, {"comment": "I think we all need to thank this guy for helping so many people and even if he didn't help you, imagine every single person he has helped, it wouldn't be the same world without mrbeast", "commenter_channel_name": "@CHE902", "likes": 403, "date": "5 years ago", "fetched_date": "2025-01-19 08:32:38.077308", "replies_count": null, "liked_by_creator": false}, {"comment": "I\u2019m convinced MrBeast is the unknown child of Bill Gates", "commenter_channel_name": "@cyper2217", "likes": 339, "date": "5 years ago", "fetched_date": "2025-01-19 08:32:38.116338", "replies_count": null, "liked_by_creator": false}, {"comment": "mr. beast the most unproblematic YouTuber ever.", "commenter_channel_name": "@lalpekhlui1925", "likes": 601, "date": "5 years ago", "fetched_date": "2025-01-19 08:32:38.154254", "replies_count": null, "liked_by_creator": false}, {"comment": "Thank you Jimmy for everything you do  your awesome", "commenter_channel_name": "@EddieMorales-v6d", "likes": 23, "date": "1 year ago", "fetched_date": "2025-01-19 08:32:38.192596", "replies_count": 0, "liked_by_creator": false}, {"comment": "Mr Beast: gives college student $2,000\nChris: \"heres 13 cents\"\n\n\n\n\n\n\n\nEdit: omg thanks for all the likes!", "commenter_channel_name": "@falsedragonhead", "likes": 513, "date": "4 years ago (edited)", "fetched_date": "2025-01-19 08:32:38.231211", "replies_count": null, "liked_by_creator": false}, {"comment": "Mr Beast : here's a semester's tuition.\n\n\n\n\nChris : here's 13 cents.", "commenter_channel_name": "@calebboulanger", "likes": 652, "date": "4 years ago (edited)", "fetched_date": "2025-01-19 08:32:38.271353", "replies_count": null, "liked_by_creator": false}, {"comment": "Respect for keeping the children off camera it shows you dont just care about content but the children themselves", "commenter_channel_name": "@dqfanboy5204", "likes": 264, "date": "3 years ago", "fetched_date": "2025-01-19 08:32:38.309598", "replies_count": null, "liked_by_creator": false}, {"comment": "J'adore vos vid\u00e9os MrBeast", "commenter_channel_name": "@Monsieur_kend", "likes": 2, "date": "8 months ago", "fetched_date": "2025-01-19 08:32:38.346751", "replies_count": 0, "liked_by_creator": false}, {"comment": "Money:*exists*\n\nMrBest: nah Bois give it away I don't want it", "commenter_channel_name": "@mircoplasticeater", "likes": 277, "date": "4 years ago", "fetched_date": "2025-01-19 08:32:38.386569", "replies_count": null, "liked_by_creator": false}, {"comment": "Much respect to the MrBeast family to provide gifts to hospitals for children and know you don't need to show them on camera.", "commenter_channel_name": "@carlahoward7492", "likes": 212, "date": "5 years ago", "fetched_date": "2025-01-19 08:32:38.423210", "replies_count": 0, "liked_by_creator": false}, {"comment": "\u201cMr beast\u201d will be known for history..", "commenter_channel_name": "@JamoreOropeza", "likes": 265, "date": "4 years ago", "fetched_date": "2025-01-19 08:32:38.461443", "replies_count": null, "liked_by_creator": false}, {"comment": "Que Bendicion Para Toda La Gente Que Ayudas...Como Quisiera Ser Parte De Tu Equipo De Trabajo...Soy De Ecuador Una Persona Muy Umilde Pero Con Un Gran Corazon De Querer Poder Ayudar A La Gente Mas Necesitada De Mi Pueblo Y Pais...DIOS TE BENDIGA MR BEAST A TI TU FAMILIA Y TODO TU GRUPO DE TRABAJO...ESPERO   LEAS ESTE MENSAJE...", "commenter_channel_name": "@franparaza486", "likes": 34, "date": "1 year ago", "fetched_date": "2025-01-19 08:32:38.500067", "replies_count": null, "liked_by_creator": false}, {"comment": "Thank you mr. Beast! You and your friends have done more for the community than news media and government themselves. You and many others are single-handedly saving this planet and helping others feel happy. Thank you for helping our community!", "commenter_channel_name": "@wheathins5945", "likes": 222, "date": "5 years ago", "fetched_date": "2025-01-19 08:32:38.539664", "replies_count": null, "liked_by_creator": false}, {"comment": "I can't believe that a person would go out of their way to make sure every that all the money he has is spent. This is the example of one of the best people the world has to offer. he does everything that anyone would want, he entertains, he gives thousands to charity, and I just want to say thank for Mr Beast for being alive, and bein the best there ever was", "commenter_channel_name": "@golam9589", "likes": 578, "date": "5 years ago", "fetched_date": "2025-01-19 08:32:38.579334", "replies_count": null, "liked_by_creator": false}, {"comment": "mr. beast has such chaotic good energy", "commenter_channel_name": "@isabellawarner8974", "likes": 219, "date": "5 years ago", "fetched_date": "2025-01-19 08:32:38.617979", "replies_count": null, "liked_by_creator": false}], "related": []}