{
    "name": "emma chamberlain",
    "is_verified": true,
    "about": "other stuff i do, \nlisten to me talk on my podcast \"Anything Goes,\" available for free anywhere you stream podcasts. watch video episodes on spotify and youtube. new episodes every thursday and sunday. \nfind my coffee company online at www.chamberlaincoffee.com, on social media @chamberlaincoffee, and possibly at a grocery store near you...",
    "links": [
        {
            "title": "my podcast (youtube)",
            "url": "youtube.com/channel/UCJvR4zNAPRJoMDF3A912dBA"
        },
        {
            "title": "my podcast (spotify)",
            "url": "open.spotify.com/show/5VzFvh1JlEhBMS6ZHZ8CNO?si=QFWUPkEaRBiXEwHXneo4HQ&nd=1"
        },
        {
            "title": "instagram",
            "url": "instagram.com/emmachamberlain"
        },
        {
            "title": "chamberlain coffee",
            "url": "chamberlaincoffee.com"
        },
        {
            "title": "spotify",
            "url": "open.spotify.com/user/emmachambie"
        }
    ],
    "subscribers": 12000000,
    "videos_count": 297,
    "views_count": 1671755539,
    "joined_date": "14 Jun 2016",
    "location": ""
}